autopip.py
banner.py
pyautopip-0.1.2.dist-info/METADATA
pyautopip-0.1.2.dist-info/WHEEL
pyautopip-0.1.2.dist-info/entry_points.txt
pyautopip-0.1.2.dist-info/licenses/LICENSE
pyautopip-0.1.2.dist-info/RECORD
