Metadata-Version: 2.4
Name: pyautopip
Version: 0.1.2
Summary: Automatic dependency installer for Python scripts
License: MIT
License-File: LICENSE
Author: FrameworkPython
Author-email: amirmahdi21r21@gmail.com
Requires-Python: >=3.7,<4.0
Classifier: License :: OSI Approved :: MIT License
Classifier: Programming Language :: Python :: 3
Classifier: Programming Language :: Python :: 3.7
Classifier: Programming Language :: Python :: 3.8
Classifier: Programming Language :: Python :: 3.9
Classifier: Programming Language :: Python :: 3.10
Classifier: Programming Language :: Python :: 3.11
Classifier: Programming Language :: Python :: 3.12
Classifier: Programming Language :: Python :: 3.13
Classifier: Programming Language :: Python :: 3.14
Requires-Dist: httpx
Project-URL: Homepage, https://github.com/FrameworkPython/autopip
